karamelo/__init__.py
karamelo/karamelo.py
Karamelo-1.0.14.dist-info/LICENCE.txt
Karamelo-1.0.14.dist-info/METADATA
Karamelo-1.0.14.dist-info/WHEEL
Karamelo-1.0.14.dist-info/top_level.txt
Karamelo-1.0.14.dist-info/RECORD
