Metadata-Version: 2.1
Name: Karamelo
Version: 1.0.14
Summary: Selection menus without asking for a string input
Home-page: https://github.com/Kylyby/karamelo_dialog
Author: Kylyby
Author-email: UNKNOWN
License: GNU GPLv3
Keywords: dialog
Platform: UNKNOWN
Classifier: Development Status :: 5 - Production/Stable
Classifier: Intended Audience :: Developers
Classifier: License :: OSI Approved :: GNU General Public License v3 (GPLv3)
Classifier: Programming Language :: Python :: 3
Requires-Dist: curtsies
